{"api_accelerator_support_luxdeviceutils.md":"D_Wf_l9r","api_building_blocks_luxcore.md":"CvmYIByr","api_building_blocks_luxlib.md":"Di-ta9NI","api_building_blocks_weightinitializers.md":"BWOG2FBe","api_domain_specific_modeling_boltz.md":"Dipdb6Os","api_domain_specific_modeling_boltz_layers.md":"CDmzK67j","api_domain_specific_modeling_boltz_private.md":"BKGtZspj","api_domain_specific_modeling_boltz_vision.md":"D-2plAjo","api_lux_autodiff.md":"DKPOXx18","api_lux_contrib.md":"B2fLyxva","api_lux_distributed_utils.md":"Dn9Tpw1R","api_lux_interop.md":"5sVnwIib","api_lux_layers.md":"D3se6-G7","api_lux_utilities.md":"QoOr6irY","api_testing_functionality_luxtestutils.md":"Bphr32NS","ecosystem.md":"4DoB-bwk","index.md":"BZi9lcaP","introduction_citation.md":"BJTGkRlp","introduction_index.md":"ot5nFeYE","introduction_overview.md":"ByCoEHJ6","introduction_resources.md":"R82OD_oe","manual_autodiff.md":"EMnPEETD","manual_debugging.md":"B_QQn1-c","manual_dispatch_custom_input.md":"q0_GLvJJ","manual_distributed_utils.md":"Johd7dJ3","manual_freezing_model_parameters.md":"BI55fwfJ","manual_gpu_management.md":"DagmXhrR","manual_interface.md":"BIbvpIXW","manual_migrate_from_flux.md":"DQVavBXT","manual_nested_autodiff.md":"DyZxGiw1","manual_nn_inside_gpu_kernels.md":"Dzo-tE9v","manual_performance_pitfalls.md":"DyuTwdEL","manual_preferences.md":"B71s3qcH","manual_weight_initializers.md":"CTu1f7Xl","tutorials_advanced_1_gravitationalwaveform.md":"CeVFJNzW","tutorials_advanced_2_symbolicoptimalcontrol.md":"DLkhB3ug","tutorials_beginner_1_basics.md":"DIOmF6rS","tutorials_beginner_2_polynomialfitting.md":"C5wVCxUD","tutorials_beginner_3_simplernn.md":"CCQ1ty1Q","tutorials_beginner_4_simplechains.md":"CIwFdx-K","tutorials_index.md":"B0fLvctO","tutorials_intermediate_1_neuralode.md":"ByekFv7A","tutorials_intermediate_2_bayesiannn.md":"Bm6XEPhA","tutorials_intermediate_3_hypernet.md":"BtywO3Th"}
