{"api_lux_distributed_utils.md":"OZ5Ke0jL","api_domain_specific_modeling_boltz.md":"6nJrk5Bc","api_accelerator_support_luxcuda.md":"aOKTk1TW","index.md":"D3CQKaHX","introduction_overview.md":"BY8Ys1a7","manual_gpu_management.md":"Bqd-56Qb","api_accelerator_support_luxamdgpu.md":"CcEuTnss","manual_weight_initializers.md":"BpYCQj4J","introduction_citation.md":"DOABG9G8","api_lux_utilities.md":"CBdpU0ZF","manual_distributed_utils.md":"BBYBLpMZ","api_testing_functionality_luxtestutils.md":"Dv2W20kA","introduction_resources.md":"BCWlMSxy","api_building_blocks_luxcore.md":"D3w9YGZO","tutorials_index.md":"BGOUtUJJ","manual_dispatch_custom_input.md":"CSwBbU0q","manual_freezing_model_parameters.md":"CwZKu2AX","api_lux_switching_frameworks.md":"D0mb_cGz","api_accelerator_support_luxdeviceutils.md":"DTaek8XK","manual_interface.md":"tYgpkcSy","ecosystem.md":"BwMJ1AIU","manual_debugging.md":"0rfpt4SS","introduction_index.md":"zEYa_dEc","api_lux_contrib.md":"Cl5JGSNE","manual_migrate_from_flux.md":"BU3kL2Bt","tutorials_beginner_4_simplechains.md":"ydoRoXb8","api_building_blocks_weightinitializers.md":"Dw8fhRUK","tutorials_intermediate_3_hypernet.md":"TG1PzEhL","api_building_blocks_luxlib.md":"DxsGOF2E","tutorials_intermediate_1_neuralode.md":"DJ8TFXo0","tutorials_beginner_3_simplernn.md":"BUBTciDj","tutorials_beginner_1_basics.md":"Cz7EUdV1","tutorials_beginner_2_polynomialfitting.md":"B9IKDHah","tutorials_intermediate_2_bayesiannn.md":"BZEndsyq","api_lux_layers.md":"DFVRgo5-","tutorials_advanced_1_gravitationalwaveform.md":"CC137cv1"}
