{"api_accelerator_support_mldatadevices.md":"BOgawkk3","api_building_blocks_luxcore.md":"DGoLS4mB","api_building_blocks_weightinitializers.md":"SzX2ukLh","api_lux_autodiff.md":"DvBg4O7x","api_lux_contrib.md":"Br0HB3Xz","api_lux_distributed_utils.md":"CfEp1JJP","api_lux_interop.md":"DyxLRr81","api_lux_layers.md":"BCLnJbL3","api_lux_utilities.md":"BqlGb5IB","api_nn_primitives_activationfunctions.md":"BSx3lmYf","api_nn_primitives_luxlib.md":"CjUzvQTO","api_nn_primitives_nnlib.md":"C9D8gkKf","api_testing_functionality_luxtestutils.md":"DdyqSxs-","index.md":"3R1Rrta6","introduction_citation.md":"cJOTszZx","introduction_index.md":"Bk2NuvrZ","introduction_overview.md":"QbzcZYmr","introduction_resources.md":"CiIltz2W","introduction_updating_to_v1.md":"Bhcls6ti","manual_autodiff.md":"DkI8TfXI","manual_compiling_lux_models.md":"DlV3zkoP","manual_debugging.md":"1hmNBXGg","manual_dispatch_custom_input.md":"DC6woHCE","manual_distributed_utils.md":"DEko6QOd","manual_exporting_to_jax.md":"DvSYaV1i","manual_freezing_model_parameters.md":"B50czj-V","manual_gpu_management.md":"Cxeho3G3","manual_interface.md":"DG8exFlm","manual_migrate_from_flux.md":"hRRFlCrE","manual_nested_autodiff.md":"DS0mumVz","manual_nn_inside_gpu_kernels.md":"DdQ4z-Nf","manual_performance_pitfalls.md":"BbqqutZT","manual_preferences.md":"DvhFWdrq","manual_weight_initializers.md":"Cld-Dwwt","tutorials_advanced_1_gravitationalwaveform.md":"B238DZv_","tutorials_beginner_1_basics.md":"xWx8ro4b","tutorials_beginner_2_polynomialfitting.md":"Clv0Ir_F","tutorials_beginner_3_simplernn.md":"Dh2ckupe","tutorials_beginner_4_simplechains.md":"DVuF0tUU","tutorials_beginner_5_optimizationintegration.md":"DbUu59G1","tutorials_index.md":"2z2OGLbh","tutorials_intermediate_1_neuralode.md":"CYh4Sw-D","tutorials_intermediate_2_bayesiannn.md":"BsD7kiFw","tutorials_intermediate_3_hypernet.md":"CvOYLpUb","tutorials_intermediate_4_pinn2dpde.md":"I-EFFfu0","tutorials_intermediate_5_convolutionalvae.md":"Dd2G5bYH"}
