{"api_accelerator_support_mldatadevices.md":"DShOkhRn","api_building_blocks_luxcore.md":"DJwNjRzJ","api_building_blocks_luxlib.md":"DJ8lsa_O","api_building_blocks_weightinitializers.md":"DSZqMG-6","api_lux_autodiff.md":"foSpHCBD","api_lux_contrib.md":"Bp5nRNfx","api_lux_distributed_utils.md":"CY860JO3","api_lux_interop.md":"BeliypaH","api_lux_layers.md":"PJNblMDg","api_lux_utilities.md":"Dpo4qQXU","api_testing_functionality_luxtestutils.md":"Bq3q2L0W","ecosystem.md":"duF7_KX1","index.md":"CtOaeviK","introduction_citation.md":"Bn6fuyo_","introduction_index.md":"CBZSNKYO","introduction_overview.md":"Byyjwp17","introduction_resources.md":"DTNGGRsa","introduction_updating_to_v1.md":"B37SJ8d8","manual_autodiff.md":"NjiN8lBA","manual_debugging.md":"DgGuaVXb","manual_dispatch_custom_input.md":"Bw9CVarD","manual_distributed_utils.md":"Ei-rbJt2","manual_freezing_model_parameters.md":"DlhBEcQV","manual_gpu_management.md":"Do9oTiIg","manual_interface.md":"sRNyhXAv","manual_migrate_from_flux.md":"gchFiLwy","manual_nested_autodiff.md":"CaJmlyhm","manual_nn_inside_gpu_kernels.md":"CNqROii0","manual_performance_pitfalls.md":"Db0cm22H","manual_preferences.md":"ot7YhIJn","manual_weight_initializers.md":"BbncuT-z","tutorials_advanced_1_gravitationalwaveform.md":"cJIhknfP","tutorials_beginner_1_basics.md":"BYvzGrHp","tutorials_beginner_2_polynomialfitting.md":"CSW9UdXX","tutorials_beginner_3_simplernn.md":"BhNPCWJe","tutorials_beginner_4_simplechains.md":"myWfrVF6","tutorials_beginner_5_optimizationintegration.md":"DHejPGst","tutorials_index.md":"DIJ0jOEP","tutorials_intermediate_1_neuralode.md":"BWaDe7UZ","tutorials_intermediate_2_bayesiannn.md":"BAzMwQsb","tutorials_intermediate_3_hypernet.md":"DMhJrcpS","tutorials_intermediate_4_pinn2dpde.md":"B_gAJkob"}
